MANIFEST.in
README.rst
setup.py
docs/HISTORY.txt
docs/LICENSE.GPL
docs/LICENSE.txt
simplelayout/__init__.py
simplelayout.base.egg-info/PKG-INFO
simplelayout.base.egg-info/SOURCES.txt
simplelayout.base.egg-info/dependency_links.txt
simplelayout.base.egg-info/entry_points.txt
simplelayout.base.egg-info/namespace_packages.txt
simplelayout.base.egg-info/not-zip-safe
simplelayout.base.egg-info/requires.txt
simplelayout.base.egg-info/top_level.txt
simplelayout/base/__init__.py
simplelayout/base/block_config.py
simplelayout/base/browser.txt
simplelayout/base/config.py
simplelayout/base/configure.zcml
simplelayout/base/dependencies.zcml
simplelayout/base/dexterity.zcml
simplelayout/base/events.py
simplelayout/base/indexer.py
simplelayout/base/interfaces.py
simplelayout/base/menu.py
simplelayout/base/setuphandlers.py
simplelayout/base/testing.py
simplelayout/base/upgrades.py
simplelayout/base/utils.py
simplelayout/base/views.py
simplelayout/base/Extensions/__init__.py
simplelayout/base/Extensions/install.py
simplelayout/base/browser/__init__.py
simplelayout/base/browser/block.pt
simplelayout/base/browser/controls.pt
simplelayout/base/browser/factories.py
simplelayout/base/browser/patch_portletmanager.py
simplelayout/base/browser/simplelayout.pt
simplelayout/base/browser/resources/pxem_Jqueryplugin.js
simplelayout/base/browser/resources/simplelayout.css
simplelayout/base/browser/resources/simplelayout.js
simplelayout/base/browser/resources/icons/icon_template_1.gif
simplelayout/base/browser/resources/icons/icon_template_13.gif
simplelayout/base/browser/resources/icons/sl-layout25.gif
simplelayout/base/browser/resources/icons/sl-layout33.gif
simplelayout/base/browser/resources/icons/sl-layout50.gif
simplelayout/base/browser/resources/icons/sl_actions_sprites.png
simplelayout/base/configlet/__init__.py
simplelayout/base/configlet/configure.zcml
simplelayout/base/configlet/interfaces.py
simplelayout/base/configlet/view.py
simplelayout/base/locales/plone.pot
simplelayout/base/locales/simplelayout-manual.pot
simplelayout/base/locales/simplelayout.pot
simplelayout/base/locales/de/LC_MESSAGES/plone.po
simplelayout/base/locales/de/LC_MESSAGES/simplelayout.po
simplelayout/base/locales/en/LC_MESSAGES/simplelayout.po
simplelayout/base/profiles/default/actions.xml
simplelayout/base/profiles/default/browserlayer.xml
