Metadata-Version: 1.1
Name: simplelayout.base
Version: 4.0.6
Summary: SimpleLayout is an easy to use plone package for creating content pages
Home-page: https://github.com/4teamwork/simplelayout.base
Author: 4teamwork AG
Author-email: mailto:info@4teamwork.ch
License: GPL2
Platform: UNKNOWN
Classifier: Framework :: Plone
Classifier: Framework :: Plone :: 4.1
Classifier: Framework :: Plone :: 4.2
Classifier: Framework :: Plone :: 4.3
Classifier: Programming Language :: Python
Classifier: Topic :: Software Development :: Libraries :: Python Modules
